README.md
setup.py
comgate/Comgate.py
comgate/__init__.py
comgate.egg-info/PKG-INFO
comgate.egg-info/SOURCES.txt
comgate.egg-info/dependency_links.txt
comgate.egg-info/requires.txt
comgate.egg-info/top_level.txt
comgate/enum/CountryCodeEnum.py
comgate/enum/CurrencyCodeEnum.py
comgate/enum/LanguageCodeEnum.py
comgate/enum/PaymentMethodCodeEnum.py
comgate/enum/PaymentStatusCodeEnum.py
comgate/enum/__init__.py
comgate/http/HttpClient.py
comgate/http/Response.py
comgate/http/__init__.py
comgate/model/Payment.py
comgate/model/__init__.py